cli_exit_tools/__init__.py
cli_exit_tools/__init__conf__.py
cli_exit_tools/cli_exit_tools.py
cli_exit_tools/cli_exit_tools_cli.py
cli_exit_tools/py.typed
cli_exit_tools-1.2.6.dist-info/LICENSE
cli_exit_tools-1.2.6.dist-info/METADATA
cli_exit_tools-1.2.6.dist-info/WHEEL
cli_exit_tools-1.2.6.dist-info/entry_points.txt
cli_exit_tools-1.2.6.dist-info/top_level.txt
cli_exit_tools-1.2.6.dist-info/RECORD
