Metadata-Version: 2.1
Name: cli_exit_tools
Version: 1.2.6
Summary: functions to exit an cli application properly
Author-email: Robert Nowotny <bitranox@gmail.com>
License: MIT
Project-URL: Homepage, https://github.com/bitranox/cli_exit_tools
Project-URL: Documentation, https://github.com/bitranox/cli_exit_tools/blob/master/README.rst
Project-URL: Repository, https://github.com/bitranox/cli_exit_tools.git
Project-URL: Changelog, https://github.com/bitranox/cli_exit_tools/blob/master/CHANGES.rst
Classifier: Development Status :: 5 - Production/Stable
Classifier: Intended Audience :: Developers
Classifier: License :: OSI Approved :: MIT License
Classifier: Natural Language :: English
Classifier: Operating System :: OS Independent
Classifier: Programming Language :: Python
Classifier: Topic :: Software Development :: Libraries :: Python Modules
Requires-Python: >=3.8.0
Provides-Extra: test
License-File: LICENSE
